weeks/week-02/rtl-dv/adder_tb/adder.v
//adder.v Design Under Take (DUT)
module adder #(parameter WIDTH=4)(
	input [WIDTH-1:0]a,
	input [WIDTH-1:0]b,
	input cin,
	output [WIDTH-1:0]sum,
	output cout);
assign {cout, sum}=a+b+cin;

endmodule;

weeks/week-02/rtl-dv/adder_tb/adder_tb.v
`timescale 1ns/1ps

module adder_tb;

	reg[3:0] a;
	reg[3:0] b;
	reg cin;
	wire[3:0] sum;
	wire cout;
	reg[3:0]error;

	adder #(.WIDTH(4)) dut (
		.a(a),
		.b(b),
		.cin(cin),
		.sum(sum),
		.cout(cout)
);

initial begin
	$dumpfile("adder.vcd");
	$dumpvars(0,adder_tb);
end

task check;
	input[3:0] ta;
	input[3:0] tb;
	input tc;
	input[4:0] expec;
	begin
		a=ta;
		b=tb;
		cin=tc;
		#10;
		if ({cout,sum}==expec) 
			$display("PASS | a=%0d b=%0d cin=%0d => ans=%0d",a,b,cin,{cout,sum});
		else
			$display("FAIL | a=%0d b=%0d cin=%0d => expected: %0d but got %0d",a, b, cin, expec, {cout,sum});
	end
endtask

initial begin
	error=0;
	$display("===Testbench===");
	
	//manual check
	$display("--Manual check--");
	check(4'd0,4'd0,0,5'd0);
	check(4'd10, 4'd10,0,5'd20);
	check(4'd15, 4'd15,1,5'd31);
	
	//random test
	$display("--Random check--");
	repeat(10) begin
		a=$random;
		b=$random;
		cin=$random;
		#10;
		if ({cout,sum} === (a+b+cin))
			$display("PASS");
		else begin
			$display("FAIL");
			error=error+1;
		end
	end
	
	$display("==DONE==");
	if (error==0)
		$display("ALL PASS!");
	else
		$display("FAIL, ERRORS: %0d",error);
	$finish;
end
endmodule

weeks/week-02/rtl-dv/adder_tb/adder.vcd
$date
	Mon Mar  2 17:13:52 2026
$end
$version
	Icarus Verilog
$end
$timescale
	1ps
$end
$scope module adder_tb $end
$var wire 4 ! sum [3:0] $end
$var wire 1 " cout $end
$var reg 4 # a [3:0] $end
$var reg 4 $ b [3:0] $end
$var reg 1 % cin $end
$var reg 4 & error [3:0] $end
$scope module dut $end
$var wire 4 ' a [3:0] $end
$var wire 4 ( b [3:0] $end
$var wire 1 % cin $end
$var wire 4 ) sum [3:0] $end
$var wire 1 " cout $end
$var parameter 32 * WIDTH $end
$upscope $end
$scope task check $end
$var reg 5 + expec [4:0] $end
$var reg 4 , ta [3:0] $end
$var reg 4 - tb [3:0] $end
$var reg 1 . tc $end
$upscope $end
$upscope $end
$enddefinitions $end
$comment Show the parameter values. $end
$dumpall
b100 *
$end
#0
$dumpvars
0.
b0 -
b0 ,
b0 +
b0 )
b0 (
b0 '
b0 &
0%
b0 $
b0 #
0"
b0 !
$end
#10000
1"
b100 !
b100 )
b1010 $
b1010 (
b1010 #
b1010 '
b10100 +
b1010 -
b1010 ,
#20000
b1111 !
b1111 )
1%
b1111 $
b1111 (
b1111 #
b1111 '
b11111 +
1.
b1111 -
b1111 ,
#30000
0"
b110 !
b110 )
b1 $
b1 (
b100 #
b100 '
#40000
1"
b1 !
b1 )
b1101 $
b1101 (
b11 #
b11 '
#50000
0"
b1000 !
b1000 )
b10 $
b10 (
b101 #
b101 '
#60000
b100 !
b100 )
1"
b110 $
b110 (
b1101 #
b1101 '
#70000
b1010 !
b1010 )
b1100 $
b1100 (
#80000
0"
b1011 !
b1011 )
0%
b101 $
b101 (
b110 #
b110 '
#90000
b1100 !
b1100 )
b111 $
b111 (
b101 #
b101 '
#100000
b1 !
b1 )
1"
b10 $
b10 (
b1111 #
b1111 '
#110000
b1101 !
b1101 )
0"
b101 $
b101 (
b1000 #
b1000 '
#120000
b1011 !
b1011 )
1"
1%
b1101 $
b1101 (
b1101 #
b1101 '
