weeks/week-04/rtl-dv/axi4-stream_scoreboard/axis_dut.v
module axis #(
  parameter int DATA_W = 32,
  parameter int KEEP_W = DATA_W / 8
)(
	input clk, rst_n,
	
	// Slave port
	input [DATA_W-1:0] s_tdata,
	input [KEEP_W-1:0] s_tkeep,
	input [7:0] s_tid,
	input s_tlast,
	input s_tvalid,
	output s_tready,

	// Master port
	output reg [DATA_W-1:0] m_tdata,
	output reg m_tvalid,
	output reg [KEEP_W-1:0] m_tkeep,
	output reg [7:0] m_tid,
	output reg m_tlast,
	input m_tready
);
assign s_tready=!m_tvalid||m_tready;
always @(posedge clk or negedge rst_n) begin
	if (!rst_n) begin
		m_tvalid<=1'b0;
		m_tdata<='0;
		m_tkeep<='0;
		m_tid<='0;
		m_tlast<=1'b0;
	end else begin
		if (s_tready) begin
			if (s_tvalid) begin
				m_tdata<=s_tdata;
				m_tkeep<=s_tkeep;
				m_tid<=s_tid;
				m_tvalid<=1'b1;
				m_tlast<=s_tlast;
			end else begin
				m_tvalid<=1'b0;
			end
		end 
	end
end
endmodule

weeks/week-04/rtl-dv/axi4-stream_scoreboard/axis_tb.v
`timescale 1ns/1ps
`define TDATA_W 32
`define TKEEP_W 4
`define TID_W 8
`define TDEST_W 4
`define TXN_W 64
`define SB_DEPTH 1024

module axis_tb;

reg clk,rst_n;
//Slave 
reg [`TDATA_W-1:0] s_tdata;
reg [`TKEEP_W-1:0] s_tkeep;
reg [`TID_W-1:0] s_tid;
reg s_tlast;
reg s_tvalid;
wire s_tready;
//Master
wire [`TDATA_W-1:0] m_tdata;
wire [`TKEEP_W-1:0] m_tkeep;
wire [`TID_W-1:0] m_tid;
wire m_tlast;
wire m_tvalid;
reg m_tready;

axis dut (
    .clk(clk),
    .rst_n(rst_n),

    .s_tdata  (s_tdata),
    .s_tkeep  (s_tkeep),
    .s_tid    (s_tid),
    .s_tlast  (s_tlast),
    .s_tvalid (s_tvalid),
    .s_tready (s_tready),

    .m_tdata  (m_tdata),
    .m_tkeep  (m_tkeep),
    .m_tid    (m_tid),
    .m_tlast  (m_tlast),
    .m_tvalid (m_tvalid),
    .m_tready (m_tready)
);

initial clk=0;
always #5 clk= ~clk;

reg [`TXN_W-1:0] exp_q [0:`SB_DEPTH-1]; 
reg [`TXN_W-1:0] act_q [0:`SB_DEPTH-1]; 
integer          exp_head, exp_tail;    
integer          act_head, act_tail;    

initial begin
	exp_head=0;
	exp_tail=0;
	act_head=0;
	act_tail=0;
end

integer cycle_count,cou;
initial cycle_count=0;
always @(posedge clk) cycle_count=cycle_count+1;

reg [31:0] sent_cycle[0:`SB_DEPTH-1];
reg [31:0] recv_cycle[0:`SB_DEPTH-1];
integer sb_pass, lat_cyc, sb_fail,sb_total;
initial begin
	sb_pass=0;
	sb_fail=0;
	lat_cyc=0;
	sb_total=0;
end

always @(posedge clk) begin
	if (rst_n && s_tvalid && s_tready) begin
		exp_q[exp_tail]<={s_tdata, s_tkeep, s_tid, 4'b0, s_tlast, 15'b0}; //use the same destination so tdest is always 0
		sent_cycle[exp_tail]<=cycle_count;
		exp_tail<=exp_tail+1;
	end
end

always @(posedge clk) begin
        if (rst_n && m_tvalid && m_tready) begin
                act_q[act_tail]<={m_tdata, m_tkeep, m_tid, 4'b0, m_tlast, 15'b0};          
                recv_cycle[act_tail]<=cycle_count;
                act_tail<=act_tail+1;
        end
end

always @(posedge clk) begin
	if (rst_n && (act_tail>act_head) &&(exp_tail>exp_head)) begin
		sb_total=sb_total+1;
		if (act_q[act_head]===exp_q[exp_head]) begin
			sb_pass=sb_pass+1;
			lat_cyc=recv_cycle[act_head]-sent_cycle[exp_head];
		end else begin
			sb_fail=sb_fail+1;
			$display("DIFF: XOR mask=%h",act_q[act_head]^exp_q[exp_head]);
		end
		exp_head=exp_head+1;
		act_head=act_head+1;
	end
end

localparam BP_PROB=30;
reg bp_enable, force_low;
initial bp_enable=0;
initial force_low=0;
always @(posedge clk or negedge rst_n) begin
	if (!rst_n)
		m_tready<=1'b1;
	else if (force_low) 
		m_tready<=1'b0;
	else if (bp_enable)
		m_tready <= ($urandom_range(0,99)) >=BP_PROB;
	else m_tready<=1'b1;
end

localparam MAX_STALL=1000;
integer stall_counter,last_act_tail;

initial begin
	stall_counter=0;
	last_act_tail=0;
end

always @(posedge clk) begin
	if (act_tail==last_act_tail && exp_tail>exp_head)
		stall_counter=stall_counter+1;
	else begin
		stall_counter=0;
		last_act_tail=act_tail;
	end
	if (stall_counter>=MAX_STALL) begin
		$display("DEADLOCK detected");
		$finish;
	end
end

task apply_reset;
    begin
        rst_n    = 1'b0;
        s_tvalid = 1'b0;
        s_tdata  = 0;
        s_tkeep  = 0;
        s_tid    = 0;
        s_tlast  = 0;
	bp_enable= 0;
        m_tready = 1'b1;
        repeat(4) @(posedge clk);
        rst_n = 1'b1;
        @(posedge clk);
    end
endtask

task print_summary;
    input [63:0] test_id;
    begin
        $display("--------------------------------------------");
        $display("Test %0d complete  pass=%0d  fail=%0d  total=%0d",
                 test_id, sb_pass-cou, sb_fail, sb_total-cou);
        $display("--------------------------------------------");
    end
endtask

task send_beat;
	input [`TDATA_W-1:0] data;
	input [`TKEEP_W-1:0] keep;
	input [`TID_W-1:0] id;
	input last;
	begin
		@(posedge clk);
		s_tdata=data;
		s_tkeep=keep;
		s_tid=id;
		s_tlast=last;
		s_tvalid=1'b1;
		//wait for s_tready and s_tready
		while (!s_tready) @(posedge clk);
		#1;
		s_tvalid=1'b0;
	end
endtask

task send_packet;
	input integer n_beats;
	input [`TID_W-1:0] id;
	integer i;
	begin
		for (i=0; i<n_beats; i=i+1) begin
			send_beat($random, 4'b1111, id, (i==n_beats-1));
		end
	end
endtask

initial begin
	$dumpfile("tb_output.vcd");
	$dumpvars(0,dut);
	rst_n=0;
	apply_reset;
	cou=0;
	$display("reset check");
	@(posedge clk); #1;
	if (m_tvalid!=1'b0) $display("[FAIL] reset fail");
	else $display("[PASS] reset success");
	
	//send input and process output
	$display("single beat sending check");
	send_beat(32'h906, 4'b1111, 8'hAF, 1'b1);
	repeat(6) @(posedge clk);
	#1;
	if (sb_fail==0 && sb_total==1) $display("[PASS] single beat sent successfully, lat=%0d cycle", lat_cyc);
	else $display("[FAIL] single beat sent fail");
	cou=sb_total;

	//send 8 8-bit packets
	$display("8-bit sending check");
	apply_reset;
   	send_packet(8, 8'h01);
    	repeat(6) @(posedge clk);
    	if (sb_fail == 0 && sb_total == cou+8)
        	$display("[PASS] 8-bit beats sending successfully");
    	else
        	$display("[FAIL] 8-bit sending fail: pass=%0d fail=%0d total=%0d", sb_pass-cou, sb_fail-cou, sb_total-cou);
	cou=sb_total;

	//sending with back pressure
	$display("back-pressure check");
	apply_reset;
	@(posedge clk); #1;
	s_tdata=32'hF00D;
	s_tkeep=4'hF;
	s_tid=8'h69;
	s_tlast=1'b1;
	s_tvalid=1'b1;
	force_low=1'b1; //hold back-pressure for checking
	repeat(5) @(posedge clk);
	//data should be held
	if (m_tvalid == 1'b1 && m_tdata==32'hF00D) 
		$display("[PASS] back-pressure successful");
	else $display("[FAIL] back-pressure fail");
	force_low=1'b0;
	@(posedge clk);
	#1;
	s_tvalid=1'b0;
	repeat(4) @(posedge clk);
	cou=sb_total;

	//idle bundle
	$display("idle-bundle checking");
	apply_reset;
	send_beat(32'hABAB, 4'hF, 8'h5, 1'b0);
	repeat(5) @(posedge clk);
	if (m_tvalid!=1'b0)
		$display("[FAIL] m_tvalid did not deassert");
	else 
		$display("[PASS] m_tvalid deasserted correctly");
	send_beat(32'hDADA, 4'hF, 8'h22, 1'b1);
	repeat(4) @(posedge clk);
	cou=sb_total;

	//100 random tests with no back-pressure
	$display("100 random beats, no back-pressure");
	apply_reset;
	begin: ran1_block //create a name to declare new vars inside this block
		integer j;
		reg [`TDATA_W-1:0] rdata;
        	reg [`TKEEP_W-1:0] rkeep;
        	reg [`TID_W-1:0] rid;
        	reg rlast;
		for (j=0; j<100; j=j+1) begin
			rdata=$random;
			case ($urandom_range(0,3))
				0: rkeep=4'b0001;
				1: rkeep=4'b0011;
				2: rkeep=4'b0111;
				3: rkeep=4'b1111;
			endcase
			rid=$random%256;
			rlast=(j%8==7) ? 1'b1: ($urandom_range(0,3)==0);
			send_beat(rdata, rkeep, rid, rlast);
		end
	end
	repeat(8) @(posedge clk);
	print_summary(1);
	cou=sb_total;
	
	//200 random tests with back-pressure
	$display("200 random beats, back-pressure enabled");
	apply_reset;
	bp_enable=1;
	begin: ran2_block //create a name to declare new vars inside this block
		integer j;
		reg [`TDATA_W-1:0] rdata;
        	reg [`TKEEP_W-1:0] rkeep;
        	reg [`TID_W-1:0] rid;
        	reg rlast;
		for (j=0; j<200; j=j+1) begin
			rdata=$random;
			case ($urandom_range(0,3))
				0: rkeep=4'b0001;
				1: rkeep=4'b0011;
				2: rkeep=4'b0111;
				3: rkeep=4'b1111;
			endcase
			rid=$random%32;
			rlast=($urandom_range(0,3)==0);
			send_beat(rdata, rkeep, rid, rlast);
		end
	end
	repeat(16) @(posedge clk);
	print_summary(2);
	cou=sb_total;

	//10 variable-length packets sendings
	$display("10 variable-length packets (1-16 beats)");
    	apply_reset;
    	bp_enable = 1;
    	begin : r3_block
        	integer pkt, len;
        	for (pkt = 0; pkt < 10; pkt = pkt + 1) begin
            		len = ($urandom_range(0,15)) + 1;
            		$display("  packet %0d: %0d beats", pkt, len);
            		send_packet(len, pkt[7:0]);
            		s_tvalid = 0;
            		repeat($urandom_range(0,4)) @(posedge clk);
        	end
    	end
    	bp_enable = 0;
    	m_tready  = 1'b1;
    	repeat(16) @(posedge clk);
    	print_summary(3);
	cou=sb_total;

	//random stress - valid and ready
	$display("random valid and random ready");
	apply_reset;
    	bp_enable = 1;
    	begin : cr4_block
        	integer i;
        	integer sent;
        	sent = 0;
        	while (sent <= 500) begin
            		@(posedge clk); #1;
            		// Random valid: present data ~70 % of cycles
            		if ($urandom_range(0,99) < 70) begin
                	s_tdata  = $random;
                	s_tkeep  = 4'hF;
                	s_tid    = $random % 8;
                	s_tlast  = ($urandom_range(0,15) == 0);
                	s_tvalid = 1'b1;
                	if (s_tready)
                    		sent = sent + 1;   // count only accepted beats
            		end else begin
                		s_tvalid = 1'b0;
            		end
        	end
        	s_tvalid = 1'b0;
    	end
    	bp_enable = 0;
    	m_tready  = 1'b1;
    	repeat(16) @(posedge clk);
    	print_summary(4);

	$display("===================================");
    	$display("  OVERALL RESULT");
    	$display("  PASS: %0d  FAIL: %0d  TOTAL: %0d", sb_pass, sb_fail, sb_total);
    	if (sb_fail == 0)
        	$display("  *** ALL TESTS PASSED ***");
    	else
        	$display("  *** %0d FAILURES DETECTED ***", sb_fail);
    	$display("===================================");
    	$finish;
end
endmodule

weeks/week-04/rtl-dv/axi4-stream_scoreboard/tb_output.vcd
$date
	Mon Mar 30 16:02:56 2026
$end
$version
	Icarus Verilog
$end
$timescale
	1ps
$end
$scope module axis_tb $end
$scope module dut $end
$var wire 1 ! clk $end
$var wire 1 " m_tready $end
$var wire 1 # rst_n $end
$var wire 32 $ s_tdata [31:0] $end
$var wire 8 % s_tid [7:0] $end
$var wire 4 & s_tkeep [3:0] $end
$var wire 1 ' s_tlast $end
$var wire 1 ( s_tready $end
$var wire 1 ) s_tvalid $end
$var parameter 32 * DATA_W $end
$var parameter 32 + KEEP_W $end
$var reg 32 , m_tdata [31:0] $end
$var reg 8 - m_tid [7:0] $end
$var reg 4 . m_tkeep [3:0] $end
$var reg 1 / m_tlast $end
$var reg 1 0 m_tvalid $end
$upscope $end
$upscope $end
$enddefinitions $end
$comment Show the parameter values. $end
$dumpall
b100 +
b100000 *
$end
#0
$dumpvars
00
0/
b0 .
b0 -
b0 ,
0)
1(
0'
b0 &
b0 %
b0 $
0#
1"
0!
$end
#5000
1!
#10000
0!
#15000
1!
#20000
0!
#25000
1!
#30000
0!
#35000
1#
1!
#40000
0!
#45000
1!
#50000
0!
#55000
1!
#60000
0!
#65000
1/
10
b10101111 -
b1111 .
b100100000110 ,
1)
1'
b10101111 %
b1111 &
b100100000110 $
1!
#66000
0)
#70000
0!
#75000
00
1!
#80000
0!
#85000
1!
#90000
0!
#95000
1!
#100000
0!
#105000
1!
#110000
0!
#115000
1!
#120000
0!
#125000
1!
#126000
0/
b0 -
b0 .
b0 ,
0'
b0 %
b0 &
b0 $
0#
#130000
0!
#135000
1!
#140000
0!
#145000
1!
#150000
0!
#155000
1!
#160000
0!
#165000
1#
1!
#170000
0!
#175000
1!
#180000
0!
#185000
10
b1 -
b1111 .
b10010000101010011010100100100 ,
1)
b1 %
b1111 &
b10010000101010011010100100100 $
1!
#186000
0)
#190000
0!
#195000
b11000000100010010101111010000001 ,
1)
b11000000100010010101111010000001 $
1!
#196000
0)
#200000
0!
#205000
b10000100100001001101011000001001 ,
1)
b10000100100001001101011000001001 $
1!
#206000
0)
#210000
0!
#215000
b10110001111100000101011001100011 ,
1)
b10110001111100000101011001100011 $
1!
#216000
0)
#220000
0!
#225000
b110101110010111101100001101 ,
1)
b110101110010111101100001101 $
1!
#226000
0)
#230000
0!
#235000
b1000110110111111001100110001101 ,
1)
b1000110110111111001100110001101 $
1!
#236000
0)
#240000
0!
#245000
b10110010110000101000010001100101 ,
1)
b10110010110000101000010001100101 $
1!
#246000
0)
#250000
0!
#255000
1/
b10001001001101110101001000010010 ,
1)
1'
b10001001001101110101001000010010 $
1!
#256000
0)
#260000
0!
#265000
00
1!
#270000
0!
#275000
1!
#280000
0!
#285000
1!
#290000
0!
#295000
1!
#300000
0!
#305000
1!
#310000
0!
#315000
0/
b0 -
b0 .
b0 ,
0'
b0 %
b0 &
b0 $
0#
1!
#320000
0!
#325000
1!
#330000
0!
#335000
1!
#340000
0!
#345000
1!
#350000
0!
#355000
1#
1!
#360000
0!
#365000
1!
#370000
0!
#375000
1!
#376000
1)
1'
b1101001 %
b1111 &
b1111000000001101 $
#380000
0!
#385000
0(
1/
10
b1101001 -
b1111 .
b1111000000001101 ,
0"
1!
#390000
0!
#395000
1!
#400000
0!
#405000
1!
#410000
0!
#415000
1!
#420000
0!
#425000
1(
1"
1!
#430000
0!
#435000
1!
#436000
0)
#440000
0!
#445000
00
1!
#450000
0!
#455000
1!
#460000
0!
#465000
1!
#470000
0!
#475000
0/
b0 -
b0 .
b0 ,
0'
b0 %
b0 &
b0 $
0#
1!
#480000
0!
#485000
1!
#490000
0!
#495000
1!
#500000
0!
#505000
1!
#510000
0!
#515000
1#
1!
#520000
0!
#525000
1!
#530000
0!
#535000
10
b101 -
b1111 .
b1010101110101011 ,
1)
b101 %
b1111 &
b1010101110101011 $
1!
#536000
0)
#540000
0!
#545000
00
1!
#550000
0!
#555000
1!
#560000
0!
#565000
1!
#570000
0!
#575000
1!
#580000
0!
#585000
1!
#590000
0!
#595000
1/
10
b100010 -
b1101101011011010 ,
1)
1'
b100010 %
b1101101011011010 $
1!
#596000
0)
#600000
0!
#605000
00
1!
#610000
0!
#615000
1!
#620000
0!
#625000
1!
#630000
0!
#635000
0/
b0 -
b0 .
b0 ,
0'
b0 %
b0 &
b0 $
0#
1!
#640000
0!
#645000
1!
#650000
0!
#655000
1!
#660000
0!
#665000
1!
#670000
0!
#675000
1#
1!
#680000
0!
#685000
1!
#690000
0!
#695000
10
b1101 -
b111 .
b111100111110001100000001 ,
1)
b1101 %
b111 &
b111100111110001100000001 $
1!
#696000
0)
#700000
0!
#705000
1/
b111101 -
b1 .
b111011001000111111000101110110 ,
1)
1'
b111101 %
b1 &
b111011001000111111000101110110 $
1!
#706000
0)
#710000
0!
#715000
0/
b10001100 -
b111 .
b1110110110101000101011111101101 ,
1)
0'
b10001100 %
b111 &
b1110110110101000101011111101101 $
1!
#716000
0)
#720000
0!
#725000
1/
b11000110 -
b1 .
b1111100111111011110100111111001 ,
1)
1'
b11000110 %
b1 &
b1111100111111011110100111111001 $
1!
#726000
0)
#730000
0!
#735000
0/
b10101010 -
b111 .
b11100010111101111000010011000101 ,
1)
0'
b10101010 %
b111 &
b11100010111101111000010011000101 $
1!
#736000
0)
#740000
0!
#745000
b1110111 -
b1110010101011111111011111100101 ,
1)
b1110111 %
b1110010101011111111011111100101 $
1!
#746000
0)
#750000
0!
#755000
b10001111 -
b1111 .
b10001001001100101101011000010010 ,
1)
b10001111 %
b1111 &
b10001001001100101101011000010010 $
1!
#756000
0)
#760000
0!
#765000
1/
b11001110 -
b1111001001100000110100111110010 ,
1)
1'
b11001110 %
b1111001001100000110100111110010 $
1!
#766000
0)
#770000
0!
#775000
0/
b11000101 -
b11 .
b11110100000000000111101011101000 ,
1)
0'
b11000101 %
b11 &
b11110100000000000111101011101000 $
1!
#776000
0)
#780000
0!
#785000
b10111101 -
b101110010110000100100101011100 ,
1)
b10111101 %
b101110010110000100100101011100 $
1!
#786000
0)
#790000
0!
#795000
1/
b1100101 -
b1 .
b10010110101010110101100000101101 ,
1)
1'
b1100101 %
b1 &
b10010110101010110101100000101101 $
1!
#796000
0)
#800000
0!
#805000
0/
b1010 -
b1111 .
b10110001111011110110001001100011 ,
1)
0'
b1010 %
b1111 &
b10110001111011110110001001100011 $
1!
#806000
0)
#810000
0!
#815000
b100000 -
b11 .
b11000000001110110010001010000000 ,
1)
b100000 %
b11 &
b11000000001110110010001010000000 $
1!
#816000
0)
#820000
0!
#825000
b10011101 -
b1010101011110000100010110101010 ,
1)
b10011101 %
b1010101011110000100010110101010 $
1!
#826000
0)
#830000
0!
#835000
1/
b10011 -
b11001011001000000011111010010110 ,
1)
1'
b10011 %
b11001011001000000011111010010110 $
1!
#836000
0)
#840000
0!
#845000
b1010011 -
b1 .
b10000110101111000011100000001101 ,
1)
b1010011 %
b1 &
b10000110101111000011100000001101 $
1!
#846000
0)
#850000
0!
#855000
0/
b11010101 -
b110101100111111101110101101011 ,
1)
0'
b11010101 %
b110101100111111101110101101011 $
1!
#856000
0)
#860000
0!
#865000
b10101110 -
b11 .
b10000001000101110100101000000010 ,
1)
b10101110 %
b11 &
b10000001000101110100101000000010 $
1!
#866000
0)
#870000
0!
#875000
b11001111 -
b1111 .
b1110111111111110100100011101 ,
1)
b11001111 %
b1111 &
b1110111111111110100100011101 $
1!
#876000
0)
#880000
0!
#885000
1/
b1010 -
b11 .
b10001100001000100100100100011 ,
1)
1'
b1010 %
b11 &
b10001100001000100100100100011 $
1!
#886000
0)
#890000
0!
#895000
b111100 -
b1 .
b11100101011100110000101011001010 ,
1)
b111100 %
b1 &
b11100101011100110000101011001010 $
1!
#896000
0)
#900000
0!
#905000
0/
b10001010 -
b111 .
b1111001011010001011110111110010 ,
1)
0'
b10001010 %
b111 &
b1111001011010001011110111110010 $
1!
#906000
0)
#910000
0!
#915000
b11011000 -
b1 .
b100000110001001011001101000001 ,
1)
b11011000 %
b1 &
b100000110001001011001101000001 $
1!
#916000
0)
#920000
0!
#925000
1/
b10001001 -
b111 .
b111100001000001111001101111000 ,
1)
1'
b10001001 %
b111 &
b111100001000001111001101111000 $
1!
#926000
0)
#930000
0!
#935000
0/
b10110110 -
b11 .
b1110101110001010000110111101011 ,
1)
0'
b10110110 %
b11 &
b1110101110001010000110111101011 $
1!
#936000
0)
#940000
0!
#945000
b10101110 -
b111 .
b1100011010010111111100111000110 ,
1)
b10101110 %
b111 &
b1100011010010111111100111000110 $
1!
#946000
0)
#950000
0!
#955000
b101010 -
b1 .
b11011110011101010000001010111100 ,
1)
b101010 %
b1 &
b11011110011101010000001010111100 $
1!
#956000
0)
#960000
0!
#965000
b1110001 -
b1111 .
b10000101110101111001101000001011 ,
1)
b1110001 %
b1111 &
b10000101110101111001101000001011 $
1!
#966000
0)
#970000
0!
#975000
b1001111 -
b11 .
b1000010111100100100000110000101 ,
1)
b1001111 %
b11 &
b1000010111100100100000110000101 $
1!
#976000
0)
#980000
0!
#985000
b111010 -
b10011101110011000110000000111011 ,
1)
b111010 %
b10011101110011000110000000111011 $
1!
#986000
0)
#990000
0!
#995000
b10101 -
b1111 .
b10111111001000110011001001111110 ,
1)
b10101 %
b1111 &
b10111111001000110011001001111110 $
1!
#996000
0)
#1000000
0!
#1005000
1/
b11011001 -
b1111000110110011001101111110001 ,
1)
1'
b11011001 %
b1111000110110011001101111110001 $
1!
#1006000
0)
#1010000
0!
#1015000
0/
b1001100 -
b11 .
b110001001000110000011101100010 ,
1)
0'
b1001100 %
b11 &
b110001001000110000011101100010 $
1!
#1016000
0)
#1020000
0!
#1025000
1/
b10001111 -
b1 .
b1001111101000010101010110011111 ,
1)
1'
b10001111 %
b1 &
b1001111101000010101010110011111 $
1!
#1026000
0)
#1030000
0!
#1035000
0/
b10110111 -
b1111 .
b1111100011011011010100111111000 ,
1)
0'
b10110111 %
b1111 &
b1111100011011011010100111111000 $
1!
#1036000
0)
#1040000
0!
#1045000
b1011100 -
b1 .
b11001111110001000101011010011111 ,
1)
b1011100 %
b1 &
b11001111110001000101011010011111 $
1!
#1046000
0)
#1050000
0!
#1055000
b10001001 -
b10101101110010111100000001011011 ,
1)
b10001001 %
b10101101110010111100000001011011 $
1!
#1056000
0)
#1060000
0!
#1065000
b11010000 -
b1111 .
b10100100101011100011001001001001 ,
1)
b11010000 %
b1111 &
b10100100101011100011001001001001 $
1!
#1066000
0)
#1070000
0!
#1075000
b1010001 -
b111 .
b11101011111111101100000011010111 ,
1)
b1010001 %
b111 &
b11101011111111101100000011010111 $
1!
#1076000
0)
#1080000
0!
#1085000
1/
b1100 -
b1111 .
b1001011001000010010111110010110 ,
1)
1'
b1100 %
b1111 &
b1001011001000010010111110010110 $
1!
#1086000
0)
#1090000
0!
#1095000
0/
b11001000 -
b11100001001011001100111011000010 ,
1)
0'
b11001000 %
b11100001001011001100111011000010 $
1!
#1096000
0)
#1100000
0!
#1105000
b111101 -
b11 .
b10111011100000100101101001110111 ,
1)
b111101 %
b11 &
b10111011100000100101101001110111 $
1!
#1106000
0)
#1110000
0!
#1115000
1/
b1111110 -
b1 .
b1001000011001101101100010010 ,
1)
1'
b1111110 %
b1 &
b1001000011001101101100010010 $
1!
#1116000
0)
#1120000
0!
#1125000
b111001 -
b1111 .
b110110111001011000000101101101 ,
1)
b111001 %
b1111 &
b110110111001011000000101101101 $
1!
#1126000
0)
#1130000
0!
#1135000
0/
b11010011 -
b11 .
b1111110100101000111100011111 ,
1)
0'
b11010011 %
b11 &
b1111110100101000111100011111 $
1!
#1136000
0)
#1140000
0!
#1145000
b1111000 -
b1 .
b1000010110110010010111110000101 ,
1)
b1111000 %
b1 &
b1000010110110010010111110000101 $
1!
#1146000
0)
#1150000
0!
#1155000
b1001001 -
b111 .
b101101110110100101100101011011 ,
1)
b1001001 %
b111 &
b101101110110100101100101011011 $
1!
#1156000
0)
#1160000
0!
#1165000
1/
b101010 -
b1111 .
b10011111111100101010111000111111 ,
1)
1'
b101010 %
b1111 &
b10011111111100101010111000111111 $
1!
#1166000
0)
#1170000
0!
#1175000
0/
b10000110 -
b1 .
b101100000101010110001101011000 ,
1)
0'
b10000110 %
b1 &
b101100000101010110001101011000 $
1!
#1176000
0)
#1180000
0!
#1185000
1/
b10011100 -
b111 .
b11000111000110100000110010001110 ,
1)
1'
b10011100 %
b111 &
b11000111000110100000110010001110 $
1!
#1186000
0)
#1190000
0!
#1195000
0/
b100110 -
b1111101001101011001100111111010 ,
1)
0'
b100110 %
b1111101001101011001100111111010 $
1!
#1196000
0)
#1200000
0!
#1205000
b10100011 -
b111001100101100001011101110011 ,
1)
b10100011 %
b111001100101100001011101110011 $
1!
#1206000
0)
#1210000
0!
#1215000
1/
b10110011 -
b1111 .
b10010111100110011010100000101111 ,
1)
1'
b10110011 %
b1111 &
b10010111100110011010100000101111 $
1!
#1216000
0)
#1220000
0!
#1225000
0/
b1000100 -
b111 .
b10101111110110000101011001011111 ,
1)
0'
b1000100 %
b111 &
b10101111110110000101011001011111 $
1!
#1226000
0)
#1230000
0!
#1235000
b11001011 -
b1 .
b1111011111110001111110111110111 ,
1)
b11001011 %
b1 &
b1111011111110001111110111110111 $
1!
#1236000
0)
#1240000
0!
#1245000
1/
b1011010 -
b111 .
b11110011000010010001101011100110 ,
1)
1'
b1011010 %
b111 &
b11110011000010010001101011100110 $
1!
#1246000
0)
#1250000
0!
#1255000
0/
b11101101 -
b11 .
b10100110011111100000100101001 ,
1)
0'
b11101101 %
b11 &
b10100110011111100000100101001 $
1!
#1256000
0)
#1260000
0!
#1265000
b1100101 -
b11101101010100110110110011011010 ,
1)
b1100101 %
b11101101010100110110110011011010 $
1!
#1266000
0)
#1270000
0!
#1275000
b11011111 -
b1 .
b11011010100010101110001010110101 ,
1)
b11011111 %
b1 &
b11011010100010101110001010110101 $
1!
#1276000
0)
#1280000
0!
#1285000
1/
b1000100 -
b11 .
b111100111100010001100101111001 ,
1)
1'
b1000100 %
b11 &
b111100111100010001100101111001 $
1!
#1286000
0)
#1290000
0!
#1295000
b101010 -
b11101000011101000000110011010000 ,
1)
b101010 %
b11101000011101000000110011010000 $
1!
#1296000
0)
#1300000
0!
#1305000
0/
b1110 -
b111 .
b1010101111101101010110110101011 ,
1)
0'
b1110 %
b111 &
b1010101111101101010110110101011 $
1!
#1306000
0)
#1310000
0!
#1315000
b10011010 -
b11 .
b1101110010111011010110111011100 ,
1)
b10011010 %
b11 &
b1101110010111011010110111011100 $
1!
#1316000
0)
#1320000
0!
#1325000
1/
b11000011 -
b111 .
b11111110110111110111001011111101 ,
1)
1'
b11000011 %
b111 &
b11111110110111110111001011111101 $
1!
#1326000
0)
#1330000
0!
#1335000
0/
b1001110 -
b101011000011101110110101010110 ,
1)
0'
b1001110 %
b101011000011101110110101010110 $
1!
#1336000
0)
#1340000
0!
#1345000
1/
b1010 -
b11 .
b10110011110110010111011001100111 ,
1)
1'
b1010 %
b11 &
b10110011110110010111011001100111 $
1!
#1346000
0)
#1350000
0!
#1355000
0/
b111000 -
b1011011011011111011100110110110 ,
1)
0'
b111000 %
b1011011011011111011100110110110 $
1!
#1356000
0)
#1360000
0!
#1365000
b10111000 -
b111 .
b111100110100011000011101111001 ,
1)
b10111000 %
b111 &
b111100110100011000011101111001 $
1!
#1366000
0)
#1370000
0!
#1375000
b10010011 -
b11 .
b1001010011101001011111110010100 ,
1)
b10010011 %
b11 &
b1001010011101001011111110010100 $
1!
#1376000
0)
#1380000
0!
#1385000
b1011001 -
b1111 .
b10000010001111110010110000000100 ,
1)
b1011001 %
b1111 &
b10000010001111110010110000000100 $
1!
#1386000
0)
#1390000
0!
#1395000
b1001101 -
b1101101110010110110100111011011 ,
1)
b1001101 %
b1101101110010110110100111011011 $
1!
#1396000
0)
#1400000
0!
#1405000
1/
b1101101 -
b11 .
b1101100101100001011011111011001 ,
1)
1'
b1101101 %
b11 &
b1101100101100001011011111011001 $
1!
#1406000
0)
#1410000
0!
#1415000
0/
b11001010 -
b10111011010001011110001001110110 ,
1)
0'
b11001010 %
b10111011010001011110001001110110 $
1!
#1416000
0)
#1420000
0!
#1425000
1/
b10010101 -
b111 .
b1011011000101110010110110110110 ,
1)
1'
b10010101 %
b111 &
b1011011000101110010110110110110 $
1!
#1426000
0)
#1430000
0!
#1435000
0/
b100 -
b1 .
b10100011000001110001101001000110 ,
1)
0'
b100 %
b1 &
b10100011000001110001101001000110 $
1!
#1436000
0)
#1440000
0!
#1445000
b1101001 -
b1111011110100100110000111110111 ,
1)
b1101001 %
b1111011110100100110000111110111 $
1!
#1446000
0)
#1450000
0!
#1455000
b10001000 -
b11 .
b11011010011011101011101010110100 ,
1)
b10001000 %
b11 &
b11011010011011101011101010110100 $
1!
#1456000
0)
#1460000
0!
#1465000
1/
b101101 -
b1111 .
b10100011111001101100100101000 ,
1)
1'
b101101 %
b1111 &
b10100011111001101100100101000 $
1!
#1466000
0)
#1470000
0!
#1475000
0/
b101110 -
b1 .
b11100011110001010011000011000111 ,
1)
0'
b101110 %
b1 &
b11100011110001010011000011000111 $
1!
#1476000
0)
#1480000
0!
#1485000
1/
b11100 -
b10000100011101111110010000001000 ,
1)
1'
b11100 %
b10000100011101111110010000001000 $
1!
#1486000
0)
#1490000
0!
#1495000
b101001 -
b1111 .
b11111110101001111010011011111101 ,
1)
b101001 %
b1111 &
b11111110101001111010011011111101 $
1!
#1496000
0)
#1500000
0!
#1505000
0/
b10000110 -
b1 .
b10001110001101111001000000011100 ,
1)
0'
b10000110 %
b1 &
b10001110001101111001000000011100 $
1!
#1506000
0)
#1510000
0!
#1515000
b111101 -
b1111 .
b11101101001101000000100011011010 ,
1)
b111101 %
b1111 &
b11101101001101000000100011011010 $
1!
#1516000
0)
#1520000
0!
#1525000
b1110000 -
b1 .
b110011010011101010011101100110 ,
1)
b1110000 %
b1 &
b110011010011101010011101100110 $
1!
#1526000
0)
#1530000
0!
#1535000
b10111010 -
b1111 .
b10111001111101010000010001110011 ,
1)
b10111010 %
b1111 &
b10111001111101010000010001110011 $
1!
#1536000
0)
#1540000
0!
#1545000
b11111010 -
b11 .
b101111001110101011001101011110 ,
1)
b11111010 %
b11 &
b101111001110101011001101011110 $
1!
#1546000
0)
#1550000
0!
#1555000
1/
b11010 -
b111 .
b1101010100011100000010111010101 ,
1)
1'
b11010 %
b111 &
b1101010100011100000010111010101 $
1!
#1556000
0)
#1560000
0!
#1565000
b110111 -
b11 .
b11011100111100000000000010111001 ,
1)
b110111 %
b11 &
b11011100111100000000000010111001 $
1!
#1566000
0)
#1570000
0!
#1575000
b11000000 -
b1 .
b1001011001001110011011110010110 ,
1)
b11000000 %
b1 &
b1001011001001110011011110010110 $
1!
#1576000
0)
#1580000
0!
#1585000
0/
b10110110 -
b111 .
b10011001001011001111100100110 ,
1)
0'
b10110110 %
b111 &
b10011001001011001111100100110 $
1!
#1586000
0)
#1590000
0!
