weeks/week-04/rtl-dv/scoreboard_exercise/adder_dut.v
module adder_dut #(parameter num_width=8) (
input [2:0] oper,
input [num_width-1:0] num_a,
input [num_width-1:0] num_b,
input cin,
output reg cout,
output reg [num_width-1:0] ans,
output neg,
output zer,
output ovf );

//oper=0 -> NOT a
//oper=1 -> a+b
//oper=2 -> a-b
//oper=3 -> a AND b
//oper=4 -> a OR b
//oper=5 -> a XOR b
//oper=6 -> a shift right b positions
//oper=7 -> a shift left b positions

always @(*) begin
	cout=1'b0;
	ans='0;
	case (oper)
		3'd0: begin
			`ifdef BUG_WRONG_NUM
				ans=~num_b;
			`else ans = ~num_a;
			`endif
		end
		3'd1: begin
			`ifdef BUG_ADD_SUBTRACT
				{cout,ans}=num_a-num_b+cin;
			`elsif BUG_IGNORE_CIN
				{cout,ans} = num_a+num_b;
			`elsif BUG_TRUNCATE
				{cout,ans}= num_a[num_width-2:0]+num_b[num_width-2:0]+cin;
			`else {cout,ans}=num_a+num_b+cin;
			`endif
		end
		3'd2: begin
			`ifdef BUG_IGNORE_CIN
				ans=num_a-num_b;
			`elsif BUG_SWAP_PLACE
				ans=num_b-num_a;
			`else ans = num_a-num_b-cin;
			`endif
		end
		3'd3: begin
			`ifdef BUG_LOGICAL_AND
				ans=num_a&&num_b;
			`else ans = num_a & num_b;
			`endif
		end
		3'd4: begin
			`ifdef BUG_LOGICAL_OR
				ans=num_a||num_b;
			`else ans = num_a | num_b;
			`endif
		end
		3'd5: ans = num_a ^ num_b;
		3'd6: begin
			`ifdef BUG_WRONG_DIRECTION
				ans=num_a << num_b[$clog2(num_width)-1:0];
			`else ans = num_a >> num_b[$clog2(num_width)-1:0];
			`endif
		end
		3'd7: ans = num_a << num_b[$clog2(num_width)-1:0];
		default: begin
			cout=1'b0;
			ans={num_width{1'b0}};
		end
	endcase
end

assign neg = (ans[num_width-1]==1'b1);
assign zer = (ans == {num_width{1'b0}});
assign ovf = (oper==3'd1) ? cout : (oper==3'd2) ? (num_b > num_a) : 1'b0;
endmodule

weeks/week-04/rtl-dv/scoreboard_exercise/adder_tb.v
`timescale 1ns/1ps
module adder_tb;
	reg [2:0] oper;
	reg [7:0] num_a;
	reg [7:0] num_b;
	reg cin;
	wire cout;
	wire [7:0] ans;
	wire neg, zer, ovf;
adder_dut dut (.oper(oper),.num_a(num_a),.num_b(num_b),.cin(cin),.cout(cout),.ans(ans),.neg(neg),.zer(zer),.ovf(ovf));

localparam NOT_A = 3'd0;
localparam ADD = 3'd1;
localparam SUB = 3'd2;
localparam AND = 3'd3;
localparam OR = 3'd4;
localparam XOR = 3'd5;
localparam SHI_RI = 3'd6;
localparam SHI_LE = 3'd7;

localparam SEED=42;

integer toca, faca, suca,o0, o1, o2, o3, o4, o5, o6, o7;
initial begin
	toca=0;
	faca=0;
	suca=0;
	o0=0;
	o1=0;
	o2=0;
	o3=0;
	o4=0;
	o5=0;
	o6=0;
	o7=0;
end

reg nega, zero, ovfl;
reg cou;
reg [7:0] answ;

task check;
input [2:0] opera;
input [7:0] nin_a;
input [7:0] nin_b;
input cinp;
begin
	cou=0;
	answ='0;
	oper  = opera;
    	num_a = nin_a;
    	num_b = nin_b;
    	cin   = cinp;
    	#10;
	toca=toca+1;
	case (opera)
		NOT_A: begin
			answ=~nin_a;
			o0=o0+1;
		end
		ADD: begin
			{cou,answ} = nin_a+nin_b+cinp;
			o1=o1+1;
		end
		SUB: begin
			answ= nin_a-nin_b-cinp;
			o2=o2+1;
		end
		AND: begin
			answ = nin_a & nin_b;
			o3=o3+1;
		end
		OR: begin
			answ= nin_a | nin_b;
			o4=o4+1;
		end
		XOR: begin
			answ = nin_a ^ nin_b;
			o5=o5+1;
		end
		SHI_RI: begin
			answ = nin_a >> nin_b[2:0];
			o6=o6+1;
		end
		SHI_LE: begin
			answ = nin_a << nin_b[2:0];
			o7=o7+1;
		end
	endcase
	nega = (answ[7]==1'b1);
	zero = (answ == {8{1'b0}});
	ovfl = (opera==ADD) ? cou : (opera==SUB) ? (nin_b > nin_a) :  1'b0;

	if ((neg==nega)&&(zero==zer)&&(ovfl==ovf)&&(cou==cout)&&(answ==ans)) 
	begin
		//$display("[SUCCESS]Test passed");
		suca=suca+1;
	end else begin
		$display("[FAIL]Test failed with a=%0d, b=%0d, expected ans=%0d, actual ans=%0d",nin_a, nin_b, answ, ans);
		case (opera)
			NOT_A: $display("NOT operation");
			ADD: $display("ADD operation");
			SUB: $display("SUB operation");
			AND: $display("AND operation");
			OR: $display("OR operation");
			XOR: $display("XOR operation");
			SHI_RI: $display("SHIFT RIGHT operation");
			SHI_LE: $display("SHIFT LEFT operation");
		endcase
		faca=faca+1;
	end
end
endtask

integer i;

initial begin
	$dumpfile("out.vcd");
	$dumpvars(0, dut);
	for (i=0; i<10000; i=i+1) begin
		check($urandom_range(0,7),$urandom_range(0,255),$urandom_range(0,255),$urandom_range(0,1));
	end
	$display("+-----------------------------------------+");
	$display("|            Scoreborad result            |");
	$display("+-----------------------------------------+");
	$display("           Number of tests: %d",toca);
	$display("           Successful tests: %d",suca);
	$display("           Failed tests:  %d",faca);
	$display("+-----------------------------------------+");
	$display("|                Coverage:                |");
	$display("+-----------------------------------------+");
	$display("             NOT tests: %d",o0); 
	$display("             ADD tests: %d",o1);
	$display("             SUB tests: %d",o2);
	$display("             AND tests: %d",o3);
	$display("             OR tests: %d",o4);
	$display("             XOR tests: %d",o5);
	$display("          SHIFT LEFT tests: %d",o6);
	$display("          SHIFT RIGHT tests: %d",o7);
	$display("-------------------------------------------");
	$finish;
end
endmodule

weeks/week-04/rtl-dv/scoreboard_exercise/out.vcd
$date
	Sat Apr 11 21:04:25 2026
$end
$version
	Icarus Verilog
$end
$timescale
	1ps
$end
$scope module adder_tb $end
$scope module dut $end
$var wire 1 ! cin $end
$var wire 1 " neg $end
$var wire 8 # num_a [7:0] $end
$var wire 8 $ num_b [7:0] $end
$var wire 3 % oper [2:0] $end
$var wire 1 & zer $end
$var wire 1 ' ovf $end
$var parameter 32 ( num_width $end
$var reg 8 ) ans [7:0] $end
$var reg 1 * cout $end
$upscope $end
$upscope $end
$enddefinitions $end
$comment Show the parameter values. $end
$dumpall
b1000 (
$end
#0
$dumpvars
0*
b1000100 )
0'
0&
b100 %
b100 $
b1000000 #
0"
0!
$end
#10000
1"
0&
b11110110 )
b110010 $
b11000110 #
#20000
0&
b10111111 )
1!
b10111011 $
b10000110 #
#30000
0"
0&
b1100000 )
0!
b11111100 $
b11000110 #
b111 %
#40000
0&
b1010000 )
b11110010 $
b1010101 #
b11 %
#50000
0&
b111000 )
b11111001 $
b11000111 #
b0 %
#60000
0&
b100010 )
b10101110 $
b1100010 #
b11 %
#70000
1"
0&
b11001101 )
1!
b110001 $
b110010 #
b0 %
#80000
1'
0&
b10111011 )
0!
b11010101 $
b10010000 #
b10 %
#90000
0"
0'
0&
b11 )
b110 $
b1001 #
#100000
0&
b1101011 )
b1 $
b1101010 #
b101 %
#110000
1"
0&
b11110111 )
1!
b10010001 $
b1100111 #
b100 %
#120000
0"
0&
b11000 )
b11111001 $
b11110 #
b11 %
#130000
1"
0&
b11010000 )
0!
b10111100 $
b1101100 #
b101 %
#140000
0&
b11011000 )
1!
b11100011 $
b11011011 #
b111 %
#150000
0&
b10010000 )
0!
b101 $
b10010101 #
b10 %
#160000
0&
b11100000 )
1!
b11101 $
b10100111 #
b110 %
#170000
1'
1*
0&
b10000011 )
b11111000 $
b10001010 #
b1 %
#180000
0"
0&
b1101001 )
0*
0'
b11001111 $
b10100110 #
b101 %
#190000
1"
0&
b10000000 )
0!
b1001111 $
b1011011 #
b111 %
#200000
0&
b11101000 )
b100100 $
b11000100 #
b1 %
#210000
0"
0&
b1000 )
1!
b11001011 $
b101000 #
b11 %
#220000
0&
b100000 )
b111011 $
b11100100 #
#230000
1"
0&
b10111111 )
b10110110 $
b111111 #
b100 %
#240000
0&
b11101011 )
0!
b11000010 $
b1101001 #
#250000
0&
b10111011 )
1!
b11111 $
b10100100 #
b101 %
#260000
0"
0&
b100 )
0!
b1000111 $
b1000011 #
#270000
0&
b100110 )
b10111001 $
b10011 #
b111 %
#280000
1"
0&
b10100110 )
1!
b101111 $
b1011001 #
b0 %
#290000
0"
0&
b101000 )
b1110011 $
b1100101 #
b111 %
#300000
0&
b1111111 )
0!
b1101101 $
b1110110 #
b100 %
#310000
1"
1'
0&
b10110010 )
1!
b10111100 $
b1101111 #
b10 %
#320000
0'
0&
b10010101 )
b11010101 $
b10010101 #
b11 %
#330000
0"
0&
b1000000 )
0!
b1111110 $
b1001101 #
b111 %
#340000
1"
0&
b10010100 )
b110011 $
b10100111 #
b101 %
#350000
0&
b11000000 )
b10111100 $
b11100 #
b110 %
#360000
0"
0&
b100100 )
b10 $
b11001001 #
#370000
0&
b1100000 )
b11101100 $
b100110 #
b111 %
#380000
1"
1'
1*
0&
b11000001 )
1!
b11011011 $
b11100101 #
b1 %
#390000
0"
0&
b1111110 )
1*
b11111011 $
b10000010 #
#400000
0&
b110000 )
0*
0'
0!
b10010100 $
b11000100 #
b10 %
#410000
0&
b100 )
1!
b100 $
b10111 #
b11 %
#420000
0&
b100 )
b1110 $
b10010100 #
#430000
0&
b10010 )
0!
b10110011 $
b11110 #
#440000
1"
1'
1*
0&
b10001101 )
1!
b10101111 $
b11011101 #
b1 %
#450000
0&
b11010000 )
0*
0'
b1011100 $
b1101 #
b111 %
#460000
0"
1&
b0 )
0!
b10010011 $
b11100000 #
b110 %
#470000
0&
b101101 )
1!
b11000011 $
b11101110 #
b101 %
#480000
0&
b1010 )
b1100111 $
b1101101 #
#490000
1&
b0 )
0!
b10001011 $
b110000 #
b11 %
#500000
1"
0&
b10100000 )
b11111010 $
b101000 #
b110 %
#510000
0"
0&
b11111 )
b1100010 $
b11100000 #
b0 %
#520000
0&
b1001111 )
b1110110 $
b111001 #
b101 %
#530000
1"
0&
b10000000 )
b11010100 $
b1010100 #
#540000
0"
0&
b1111111 )
1!
b1001111 $
b1110011 #
b100 %
#550000
1"
0&
b11001111 )
0!
b11001111 $
b1000110 #
#560000
1'
1*
0&
b11001010 )
1!
b11100101 $
b11100100 #
b1 %
#570000
0&
b10111000 )
0*
0'
b11011011 $
b1100011 #
b101 %
#580000
0&
b10111000 )
0!
b11001001 $
b11011100 #
b111 %
#590000
0&
b10111110 )
b11111101 $
b1000011 #
b101 %
#600000
0&
b11011110 )
b11000010 $
b1011110 #
b100 %
#610000
0&
b11010100 )
1!
b1010000 $
b11010100 #
b111 %
#620000
0"
0&
b101 )
b1110111 $
b101 #
b11 %
#630000
0&
b1111111 )
b1000111 $
b111010 #
b100 %
#640000
1"
0&
b11100000 )
b11001101 $
b1010111 #
b110 %
#650000
0&
b10110111 )
0!
b10100101 $
b10110 #
b100 %
#660000
0"
0&
b1111001 )
1!
b11110110 $
b10000110 #
b0 %
#670000
0&
b1000011 )
0!
b100000 $
b1000011 #
b111 %
#680000
0&
b1001000 )
b101011 $
b10101001 #
#690000
1&
b0 )
b10111001 $
b10 #
b11 %
#700000
0&
b1011100 )
b11100 $
b1011100 #
b100 %
#710000
1"
1'
0&
b11010100 )
1!
b11000000 $
b10010101 #
b10 %
#720000
0'
0&
b11011111 )
0!
b1111 $
b11010000 #
b100 %
#730000
0&
b11000001 )
b10001010 $
b1001011 #
b101 %
#740000
1'
0&
b10101110 )
b10101010 $
b1011000 #
b10 %
#750000
0'
0&
b11111110 )
b11010110 $
b11111010 #
b100 %
#760000
0&
b10011000 )
b1110011 $
b1010011 #
b110 %
#770000
1'
1*
0&
b11010010 )
1!
b11100100 $
b11101101 #
b1 %
#780000
0&
b10011000 )
0*
0!
b11111101 $
b10010101 #
b10 %
#790000
0"
0'
0&
b1111100 )
b111001 $
b111110 #
b110 %
#800000
1"
0&
b11111011 )
1!
b11000011 $
b110111 #
b1 %
#810000
0&
b10110100 )
b10100 $
b10100000 #
b100 %
#820000
0&
b10100000 )
b10111010 $
b11100000 #
b11 %
#830000
0"
0&
b1000 )
b10010101 $
b10011110 #
b10 %
#840000
1"
0&
b11111011 )
0!
b10001011 $
b1110000 #
b100 %
#850000
0"
0&
b1100 )
1!
b10010010 $
b1000011 #
b111 %
#860000
1"
1'
0&
b10101001 )
b10000011 $
b101101 #
b10 %
#870000
0"
0'
0&
b111101 )
b11101 $
b111000 #
b100 %
#880000
0&
b1110 )
b101110 $
b1001111 #
b11 %
#890000
1"
0&
b10101111 )
0!
b10111001 $
b1010000 #
b0 %
#900000
0&
b11000000 )
b10100101 $
b110 #
b111 %
#910000
0"
0&
b1000000 )
1!
b111101 $
b1111110 #
b10 %
#920000
0&
b1110 )
b10001110 $
b11110001 #
b0 %
#930000
0&
b111010 )
0!
b1110000 $
b1001010 #
b101 %
#940000
0&
b111010 )
b11000110 $
b11111100 #
#950000
1"
0&
b11000000 )
1!
b1000110 $
b10100011 #
b110 %
#960000
0&
b11110111 )
0!
b11000010 $
b10110101 #
b100 %
#970000
0&
b11101101 )
b11011101 $
b110000 #
b101 %
#980000
0"
1'
0&
b1111001 )
b10011001 $
b10010 #
b10 %
#990000
0&
b101001 )
0'
1!
b11110 $
b1010 #
b1 %
#1000000
1'
1*
0&
b1100110 )
0!
b11000011 $
b10100011 #
#1010000
1"
0&
b11010001 )
0*
0'
1!
b10110 $
b11101000 #
b10 %
#1020000
0&
b10111101 )
b10001000 $
b110101 #
b100 %
#1030000
1'
1*
0&
b10110000 )
b11110110 $
b10111001 #
b1 %
#1040000
0"
0&
b1000000 )
0*
0'
0!
b11100 $
b11100100 #
b110 %
#1050000
1"
0&
b10000010 )
1!
b11001110 $
b10110011 #
b11 %
#1060000
0"
0&
b1000000 )
b1101100 $
b10100100 #
b110 %
#1070000
0&
b110110 )
0!
b11110001 $
b11001001 #
b0 %
#1080000
0&
b1100 )
1!
b10011101 $
b101110 #
b11 %
#1090000
0&
b1100011 )
0!
b1001 $
b10011100 #
b0 %
#1100000
0&
b1011111 )
1!
b110111 $
b1101000 #
b101 %
#1110000
0&
b1100000 )
0!
b11011101 $
b11010011 #
b111 %
#1120000
1"
0&
b11001011 )
1!
b110 $
b110100 #
b0 %
#1130000
0&
b11100111 )
0!
b11001000 $
b11100111 #
b111 %
#1140000
0"
1'
1*
0&
b1100000 )
b10100101 $
b10111011 #
b1 %
#1150000
0&
b100000 )
0*
0'
b11011100 $
b1100010 #
b110 %
#1160000
1'
0&
b1011100 )
1!
b10111011 $
b11000 #
b10 %
#1170000
0'
0&
b11000 )
b10000011 #
b111 %
#1180000
1&
b0 )
0!
b11101101 $
b10000000 #
b110 %
#1190000
0&
b1100010 )
b11000 $
b1100010 #
b111 %
#1200000
1'
1*
0&
b1001100 )
1!
b1110100 $
b11010111 #
b1 %
#1210000
1"
0&
b10001000 )
0*
0'
0!
b11110000 $
b1110111 #
b0 %
#1220000
0"
0&
b110000 )
b1110010 $
b10110000 #
b11 %
#1230000
1"
0&
b11100100 )
b1110000 $
b10010100 #
b101 %
#1240000
0"
0&
b101010 )
1!
b11101010 $
b11000000 #
#1250000
1"
0&
b10000000 )
0!
b10000111 $
b1010101 #
b111 %
#1260000
0"
1'
1*
0&
b111001 )
1!
b1110001 $
b11000111 #
b1 %
#1270000
1"
0&
b11001010 )
0*
0'
0!
b101101 $
b11110111 #
b10 %
#1280000
0"
0&
b1010101 )
1!
b10001001 $
b11011100 #
b101 %
#1290000
1"
0&
b11110011 )
0!
b1011011 $
b10101000 #
#1300000
0&
b11000111 )
b10110001 $
b111000 #
b0 %
#1310000
0&
b10111110 )
1!
b10101100 $
b111110 #
b100 %
#1320000
0"
0&
b1100100 )
b100000 $
b1100100 #
b111 %
#1330000
0&
b100000 )
0!
b10111000 $
b1100110 #
b11 %
#1340000
1"
0&
b10101000 )
1!
b110101 $
b11011110 #
b10 %
#1350000
0"
0&
b1001111 )
0!
b10010 $
b111101 #
b1 %
#1360000
0&
b1011100 )
1!
b10010001 $
b101110 #
b111 %
#1370000
1"
0&
b10000000 )
0!
b111 $
b1011101 #
#1380000
0&
b11101111 )
b11101010 $
b1100111 #
b100 %
#1390000
0"
0&
b1100100 )
b11111010 $
b1011001 #
b110 %
#1400000
1"
0&
b10011101 )
b10000001 $
b11100 #
b100 %
#1410000
0&
b10100111 )
1!
b10100111 #
#1420000
0"
0&
b111001 )
b1010111 $
b11000110 #
b0 %
#1430000
1"
0&
b10000000 )
b100110 $
b11111010 #
b110 %
#1440000
0&
b10011000 )
0!
b110 $
b10010010 #
b1 %
#1450000
0&
b11011110 )
b11011110 $
b10100 #
b100 %
#1460000
0&
b10101000 )
1!
b1010000 $
b10101000 #
b111 %
#1470000
0"
0&
b101010 )
0!
b101110 $
b11111010 #
b11 %
#1480000
1'
1*
0&
b111010 )
b1011100 $
b11011110 #
b1 %
#1490000
0&
b11 )
0*
0'
b11 $
b10100011 #
b11 %
#1500000
1'
1*
0&
b1111101 )
b10100010 $
b11011011 #
b1 %
#1510000
0'
0&
b1000111 )
0*
b110100 $
b10011 #
#1520000
0&
b11110 )
1!
b10001110 $
b10101101 #
b10 %
#1530000
1&
b0 )
b10110111 $
b11101000 #
b110 %
#1540000
1"
1'
1*
0&
b10001100 )
b11000101 $
b11000110 #
b1 %
#1550000
0"
0&
b100000 )
0*
0'
b10001100 $
b1010010 #
b111 %
#1560000
1"
0&
b10000110 )
b101100 $
b1111001 #
b0 %
#1570000
0&
b11001110 )
b1001101 $
b10000011 #
b101 %
#1580000
0&
b10000101 )
b10001101 $
b11010101 #
b11 %
#1590000
0"
0&
b1100000 )
b1110100 $
b10000110 #
b110 %
#1600000
1"
0&
b11111000 )
b11111001 $
b11111100 #
b111 %
#1610000
0&
b11011011 )
b1010110 $
b10001101 #
b101 %
#1620000
0"
0&
b11000 )
0!
b11010101 $
b11100111 #
b0 %
#1630000
1"
1'
0&
b11101101 )
b11000001 $
b10101110 #
b10 %
#1640000
0"
0'
0&
b10 )
b10011001 $
b10011011 #
b101 %
#1650000
0&
b1 )
1!
b1010101 $
b1011 #
b11 %
#1660000
0&
b111001 )
b111000 $
b11000110 #
b0 %
#1670000
0&
b1110000 )
0!
b10001011 $
b1101110 #
b110 %
#1680000
1"
0&
b10100000 )
b1000100 $
b11011010 #
b111 %
#1690000
1'
0&
b11101111 )
b1101001 $
b1011000 #
b10 %
#1700000
0&
b11010101 )
b10111000 $
b10001101 #
#1710000
0'
0&
b10000111 )
1!
b11100110 $
b1111000 #
b0 %
#1720000
0&
b11111110 )
0!
b1110110 $
b11001100 #
b100 %
#1730000
0&
b10011100 )
b1 $
b10011011 #
b1 %
#1740000
0"
0&
b10100 )
b1110100 $
b11111 #
b11 %
#1750000
0&
b110 )
b10001001 $
b11 #
b110 %
#1760000
0&
b11011 )
1!
b10011011 $
b1111111 #
b11 %
#1770000
1"
0&
b10101000 )
0!
b10001011 $
b110101 #
b111 %
#1780000
0"
0&
b1101010 )
b1010011 $
b10010101 #
b0 %
#1790000
1&
b0 )
b10000010 $
b110101 #
b11 %
#1800000
1"
0&
b11000000 )
b11000010 $
b1110000 #
b110 %
#1810000
0"
0&
b100000 )
1!
b100011 $
b110000 #
b11 %
#1820000
1"
0&
b10111101 )
0!
b10111001 $
b10101100 #
b100 %
#1830000
0&
b10011000 )
1!
b11101000 $
b10011000 #
b111 %
#1840000
0&
b10101100 )
b1010000 $
b11111100 #
b101 %
#1850000
0"
0&
b1111000 )
0!
b1000011 $
b10101111 #
b110 %
#1860000
0&
b111101 )
b110101 $
b111000 #
b100 %
#1870000
0&
b1111001 )
1!
b10000110 $
b10000110 #
b0 %
#1880000
0&
b1100000 )
0!
b10101010 $
b11001010 #
b101 %
#1890000
0&
b1110111 )
b1110110 $
b1100001 #
b100 %
#1900000
1"
0&
b11000011 )
1!
b101111 $
b10010011 #
b1 %
#1910000
0"
0&
b111000 )
b10010001 $
b10011100 #
b110 %
#1920000
0&
b1000001 )
0!
b11100111 $
b1000001 #
b11 %
#1930000
0&
b10010 )
1!
b100 $
b11101101 #
b0 %
#1940000
1"
0&
b11010000 )
0!
b10011100 $
b1101 #
b110 %
#1950000
0"
0&
b1111010 )
1!
b1010001 $
b101000 #
b1 %
#1960000
0&
b1110110 )
0!
b10000011 $
b11110101 #
b101 %
#1970000
1'
1*
0&
b1000 )
b10100100 $
b1100100 #
b1 %
#1980000
0&
b1011010 )
0*
0'
1!
b10101000 $
b1011010 #
b111 %
#1990000
1"
0&
b10011010 )
0!
b11011000 $
b10011010 #
b110 %
#2000000
0"
0&
b10100 )
b1100 $
b11000 #
b101 %
#2010000
1"
0&
b11011101 )
1!
b101100 $
b10110000 #
b1 %
#2020000
0"
0&
b1101111 )
0!
b1101111 $
b101 #
b100 %
#2030000
1"
0&
b11111100 )
1!
b10101100 $
b11110100 #
#2040000
0&
b10101000 )
b11010010 $
b11101010 #
b111 %
#2050000
0"
0&
b1110 )
b1000001 $
b111 #
#2060000
0&
b111101 )
0!
b10100010 $
b11011111 #
b10 %
#2070000
0&
b1000110 )
1!
b1111100 $
b111010 #
b101 %
#2080000
1"
0&
b10110000 )
0!
b10011000 $
b101000 #
#2090000
0"
0&
b1010000 )
b111 $
b1010111 #
b10 %
#2100000
0&
b101100 )
1!
b1000010 $
b1101111 #
#2110000
1"
0&
b11101101 )
b11001101 $
b11100001 #
b100 %
#2120000
0"
0&
b110111 )
b1000101 $
b1111101 #
b10 %
#2130000
1"
0&
b10001000 )
b11001111 $
b10111000 #
b11 %
#2140000
0&
b10100111 )
0!
b1001000 $
b1011111 #
b1 %
#2150000
0&
b10010101 )
b10101010 $
b111111 #
b101 %
#2160000
1'
1*
0&
b10000110 )
1!
b10010010 $
b11110011 #
b1 %
#2170000
0&
b10100110 )
1*
0!
b11001010 $
b11011100 #
#2180000
0"
0&
b1010011 )
0*
0'
1!
b1010111 $
b11110011 #
b11 %
#2190000
0&
b1 )
0!
b1010101 $
b11111110 #
b0 %
#2200000
1"
0&
b11111001 )
1!
b10111001 $
b1100001 #
b100 %
#2210000
1'
0&
b11000100 )
b10111010 $
b1111111 #
b10 %
#2220000
0'
0&
b10000000 )
0!
b1101111 $
b1110001 #
b111 %
#2230000
0"
0&
b10000 )
1!
b11111001 $
b10001000 #
b110 %
#2240000
0&
b1101000 )
b101010 $
b11011010 #
#2250000
0&
b101001 )
b10011010 $
b11010110 #
b0 %
#2260000
0&
b1101000 )
0!
b10010111 #
#2270000
0&
b100110 )
b1010011 $
b1111001 #
b10 %
#2280000
0&
b100000 )
b110100 $
b100000 #
b11 %
#2290000
0&
b1011010 )
b1011010 $
b11111111 #
#2300000
1"
0&
b10100101 )
1!
b10011011 $
b1001 #
b1 %
#2310000
0"
1&
b0 )
0!
b1101101 $
b10000 #
b11 %
#2320000
1"
0&
b10100000 )
1!
b10111101 $
b10101 #
b111 %
#2330000
0"
0&
b101 )
0!
b10000101 $
b1110101 #
b11 %
#2340000
1'
1*
0&
b1100000 )
b10100010 $
b10111110 #
b1 %
#2350000
1"
0&
b11011011 )
0*
0'
b1000001 $
b10011011 #
b100 %
#2360000
0&
b10010100 )
1!
b11101010 $
b100101 #
b111 %
#2370000
0"
0&
b1110010 )
b11110110 $
b1111010 #
b11 %
#2380000
0&
b1110000 )
b11111001 $
b1110110 #
#2390000
1"
0&
b10011000 )
0!
b1110110 $
b11101110 #
b101 %
#2400000
0&
b10000000 )
1!
b11010101 $
b10111100 #
b111 %
#2410000
0"
0&
b1000000 )
b10000110 $
b10001001 #
#2420000
0&
b100100 )
0!
b10110101 $
b100100 #
b11 %
#2430000
0&
b110100 )
1!
b100 $
b11001011 #
b0 %
#2440000
0&
b1110111 )
b111011 $
b10110011 #
b10 %
#2450000
0&
b1101 )
0!
b10111101 $
b11001010 #
#2460000
1"
0&
b11001001 )
1!
b1100100 $
b1100100 #
b1 %
#2470000
0"
1&
b0 )
b11101111 $
b1010110 #
b111 %
#2480000
1"
0&
b11101001 )
b101000 $
b11000001 #
b101 %
#2490000
1'
0&
b11111001 )
0!
b10000011 $
b1111100 #
b10 %
#2500000
0'
0&
b11000000 )
b11000010 $
b11100100 #
b11 %
#2510000
0"
1&
b0 )
b11101111 $
b10001000 #
b111 %
#2520000
1"
0&
b11111011 )
b10110000 $
b11101011 #
b100 %
#2530000
0"
0&
b100000 )
1!
b11001101 $
b1101001 #
b110 %
#2540000
1"
0&
b10111000 )
b1100011 $
b11011011 #
b101 %
#2550000
0"
0&
b1110101 )
0!
b100010 $
b10010111 #
b10 %
#2560000
1"
1'
1*
0&
b10001011 )
b10010111 $
b11110100 #
b1 %
#2570000
0"
0&
b1010101 )
0*
0'
1!
b1010000 $
b1010101 #
b111 %
#2580000
0&
b1100100 )
b1100110 $
b1110100 #
b11 %
#2590000
1"
0&
b11000000 )
b10111110 $
b1101111 #
b110 %
#2600000
0&
b11001000 )
0!
b11 $
b11001011 #
b10 %
#2610000
0&
b11000000 )
1!
b101110 $
b1101011 #
b111 %
#2620000
0"
0&
b11000 )
b100111 $
b111111 #
b101 %
#2630000
1&
b0 )
b11000000 $
b11100 #
b11 %
#2640000
1"
0&
b11000000 )
0!
b101110 $
b11111111 #
b110 %
#2650000
0&
b10111111 )
b10101011 $
b10110100 #
b100 %
#2660000
0"
0&
b1001101 )
b11101001 $
b10100100 #
b101 %
#2670000
1"
0&
b11000000 )
b10011100 $
b111100 #
b111 %
#2680000
0&
b11010100 )
b10110 $
b101011 #
b0 %
#2690000
0&
b11010110 )
b11010110 $
b10000000 #
b100 %
#2700000
0&
b11011111 )
1!
b10001110 $
b1010000 #
b1 %
#2710000
0&
b11101101 )
b11101100 $
b1101101 #
b100 %
#2720000
0&
b10010000 )
0!
b101000 $
b1101000 #
b1 %
#2730000
0"
1'
1*
0&
b11000 )
b111111 $
b11011001 #
#2740000
1"
0&
b10100100 )
0*
0'
b1000000 $
b10100100 #
b111 %
#2750000
0&
b10000000 )
1!
b11111 $
b11000001 #
b110 %
#2760000
1'
1*
0&
b10111000 )
b11111000 $
b10111111 #
b1 %
#2770000
0"
0&
b1000000 )
0*
0'
0!
b10100100 $
b11110100 #
b110 %
#2780000
0&
b1100 )
b100100 $
b101000 #
b101 %
#2790000
0&
b1011011 )
b101111 $
b101100 #
b1 %
#2800000
1"
0&
b10101001 )
1'
b11101010 $
b10010011 #
b10 %
#2810000
0&
b11111011 )
b10100011 $
b10011110 #
#2820000
0"
1*
0&
b111 )
1'
1!
b1011 $
b11111011 #
b1 %
#2830000
1"
0&
b11100010 )
0*
0'
0!
b1001001 $
b11110001 #
b110 %
#2840000
0&
b11111101 )
b11100101 $
b11000 #
b101 %
#2850000
0&
b11001001 )
b1100110 $
b10101111 #
#2860000
0"
0&
b1011111 )
b11111 $
b1000001 #
b100 %
#2870000
0&
b1100100 )
1!
b10000010 $
b11001 #
b110 %
#2880000
1"
0&
b10111001 )
0!
b101 $
b10111110 #
b10 %
#2890000
0&
b11100000 )
1!
b1011010 $
b1111000 #
b111 %
#2900000
0&
b10010111 )
b10010110 $
b10010001 #
b100 %
#2910000
0"
0&
b1011101 )
b10000111 $
b11011010 #
b101 %
#2920000
1"
0&
b11100001 )
b1000101 $
b10100100 #
#2930000
0"
0&
b10101 )
0!
b11010101 $
b110101 #
b11 %
#2940000
1"
0&
b11011000 )
b1100001 $
b1101100 #
b110 %
#2950000
0"
0&
b1011000 )
1!
b1001001 $
b1110 #
b1 %
#2960000
1"
0&
b11111011 )
0!
b110110 $
b100 #
b0 %
#2970000
0&
b11101100 )
b11010010 $
b1111011 #
b110 %
#2980000
0"
0&
b1111101 )
b11011010 $
b10100111 #
b101 %
#2990000
0&
b11000 )
1!
b10110011 $
b10100011 #
b110 %
#3000000
1"
0&
b10101010 )
0!
b10101010 $
b10101010 #
b100 %
#3010000
0"
0&
b1010111 )
b10010110 $
b10101000 #
b0 %
#3020000
1"
0&
b10101011 )
1!
b1110111 $
b11011100 #
b101 %
#3030000
0"
0&
b1010100 )
0!
b1010100 $
b100 #
b100 %
#3040000
1"
0&
b10100011 )
b1100111 $
b1011100 #
b0 %
#3050000
0&
b10101011 )
1!
b1010100 #
#3060000
0&
b10100001 )
0!
b1111010 $
b11011011 #
b101 %
#3070000
0&
b10010000 )
1!
b10011 $
b10010010 #
b111 %
#3080000
0"
1'
1*
0&
b100100 )
b11010100 $
b1001111 #
b1 %
#3090000
1"
0&
b10000100 )
0*
0'
b111001 $
b11000010 #
b110 %
#3100000
0&
b10000000 )
b10011110 $
b11010 #
#3110000
0&
b11110001 )
0!
b11011110 $
b1110 #
b0 %
#3120000
0"
0&
b111011 )
b10101100 $
b10010111 #
b101 %
#3130000
0&
b1101110 )
1!
b1100000 $
b1001110 #
b100 %
#3140000
1"
0&
b11101110 )
b11001000 $
b100101 #
b1 %
#3150000
0"
0&
b1010000 )
b1011001 $
b1001 #
b101 %
#3160000
1"
0&
b10111111 )
b10101110 $
b10010101 #
b100 %
#3170000
0&
b11010000 )
b111100 $
b11011101 #
b111 %
#3180000
0&
b10110100 )
b10111011 $
b1111 #
b101 %
#3190000
0"
0&
b1011010 )
b10010000 $
b1011010 #
b111 %
#3200000
1"
0&
b10101111 )
0!
b1001001 $
b1100110 #
b1 %
#3210000
0"
0&
b1100000 )
1'
1!
b11101110 $
b1001111 #
b10 %
#3220000
1"
1*
0&
b10011101 )
1'
0!
b11000000 $
b11011101 #
b1 %
#3230000
0"
0&
b1010000 )
0*
0'
b10100100 $
b10000101 #
b110 %
#3240000
0&
b1010111 )
1!
b1010000 $
b1010111 #
b111 %
#3250000
1"
0&
b11101010 )
b110 $
b11101100 #
b101 %
#3260000
0&
b10100001 )
0!
b1011111 $
b11111110 #
#3270000
1'
0&
b10110111 )
b1111101 $
b110100 #
b10 %
